fastapi_validation/__init__.py
fastapi_validation/constants/validator_constant.py
fastapi_validation/custom_errors/value_error.py
fastapi_validation/enums/database_type_enum.py
fastapi_validation/helpers/list_init_enum_query_param.py
fastapi_validation/models/projection_model.py
fastapi_validation/types/custom_condition_type.py
fastapi_validation/validators/base.py
fastapi_validation/validators/base_exist_validator.py
fastapi_validation/validators/exist.py
fastapi_validation/validators/field_validator.py
fastapi_validation/validators/model_validator.py
fastapi_validation/validators/nosql_exists.py
fastapi_validation/validators/password.py
fastapi_validation/validators/query_list_integer_enum.py
fastapi_validation/validators/sql_exist.py
fastapi_validation/validators/unique.py
fastapi_validation-1.1.19.dist-info/METADATA
fastapi_validation-1.1.19.dist-info/WHEEL
fastapi_validation-1.1.19.dist-info/licenses/LICENSE
fastapi_validation-1.1.19.dist-info/RECORD
