Metadata-Version: 2.3
Name: fastapi_validation
Version: 1.1.19
Summary: FastAPI Validation
Project-URL: Homepage, https://github.com/megatron-global/fastapi-validation
Project-URL: Bug Tracker, https://github.com/megatron-global/fastapi-validation/issues
Author-email: Dzung Nguyen <dung@megatron-solutions.com>, Harry Dang <harrydang.tech@gmail.com>
License-File: LICENSE
Classifier: License :: OSI Approved :: MIT License
Classifier: Operating System :: OS Independent
Classifier: Programming Language :: Python :: 3
Requires-Python: >=3.10
Requires-Dist: beanie>=1.21.0
Requires-Dist: fastapi-exception>=1.3.0
Requires-Dist: fastapi-global-variable>=0.0.4
Requires-Dist: pydantic>=2.6.0
Requires-Dist: python-keycloak~=2.14.0
Requires-Dist: sqlalchemy~=2.0.4
